MANIFEST.in
README.rst
distribute_setup.py
requirements.txt
setup.cfg
setup.py
Okydoky.egg-info/PKG-INFO
Okydoky.egg-info/SOURCES.txt
Okydoky.egg-info/dependency_links.txt
Okydoky.egg-info/entry_points.txt
Okydoky.egg-info/requires.txt
Okydoky.egg-info/top_level.txt
okydoky/__init__.py
okydoky/__main__.py
okydoky/app.py
okydoky/run.py
okydoky/version.py
okydoky/templates/base.html
okydoky/templates/empty.html
okydoky/templates/home.html
okydoky/templates/list.html