Metadata-Version: 1.0
Name: Okydoky
Version: 0.9.6
Summary: Automated docs builder using Sphinx/GitHub/Distribute for private use
Home-page: https://github.com/crosspop/okydoky
Author: Hong Minhee
Author-email: dahlia@crosspop.in
License: MIT License
Platform: UNKNOWN
Classifier: Development Status :: 4 - Beta
Classifier: Environment :: Web Environment
Classifier: Intended Audience :: Developers
Classifier: Intended Audience :: System Administrators
Classifier: License :: OSI Approved :: MIT License
Classifier: Operating System :: OS Independent
Classifier: Programming Language :: Python :: 2.6
Classifier: Programming Language :: Python :: 2.7
Classifier: Programming Language :: Python :: 2 :: Only
Classifier: Topic :: Documentation
Classifier: Topic :: Software Development :: Documentation
